LICENSE
MANIFEST.in
README.rst
setup.py
cdindex/__init__.py
cdindex/cdindex.py
cdindex/pycdindex.c
cdindex/time_utilities.py
cdindex.egg-info/PKG-INFO
cdindex.egg-info/SOURCES.txt
cdindex.egg-info/dependency_links.txt
cdindex.egg-info/requires.txt
cdindex.egg-info/top_level.txt
src/cdindex.c
src/cdindex.h
src/graph.c
src/main.c
src/utility.c