Metadata-Version: 2.1
Name: cdindex
Version: 1.0.20
Summary: Package for computing the cdindex.
Home-page: http://www.cdindex.info
Author: Russell J. Funk
Author-email: russellfunk@gmail.com
License: GNU General Public License (GPL)
License-File: LICENSE
Requires-Dist: future
